GDUs/__init__.py
GDUs/calc_return.py
GDUs/get_data.py
GDUs/return_calculator.py
GD_utils/Report.py
GD_utils/__init__.py
GD_utils/calc_return.py
GD_utils/factor_calculator.py
GD_utils/general_utils.py
GD_utils/get_data.py
GD_utils/optimizers.py
GD_utils/portfolio_calculator.py
GD_utils/return_calculator.py
GD_utils/return_calculator_old.py
GD_utils-0.2.0.42.dist-info/METADATA
GD_utils-0.2.0.42.dist-info/WHEEL
GD_utils-0.2.0.42.dist-info/top_level.txt
GD_utils-0.2.0.42.dist-info/RECORD
