Metadata-Version: 2.1
Name: GD_utils
Version: 0.2.0.42
Summary: backtest tools
Home-page: https://github.com/gdpresent/GD_utils.git
Author: GD park
Author-email: gdpresent@naver.com
License: MIT
Classifier: Programming Language :: Python :: 3
Classifier: License :: OSI Approved :: MIT License
Classifier: Operating System :: OS Independent
